exploit_utils/__init__.py
exploit_utils/args.py
exploit_utils/crypto.py
exploit_utils/encode.py
exploit_utils/fs.py
exploit_utils/http.py
exploit_utils/log.py
exploit_utils/misc.py
exploit_utils/mt.py
exploit_utils/rand.py
exploit_utils/sh.py
exploit_utils-0.2.0.dist-info/METADATA
exploit_utils-0.2.0.dist-info/WHEEL
exploit_utils-0.2.0.dist-info/licenses/LICENSE
exploit_utils-0.2.0.dist-info/RECORD
