Metadata-Version: 2.4
Name: exploit_utils
Version: 0.2.0
Summary: template code for exp
License-File: LICENSE
Requires-Python: >=3.12
Requires-Dist: cryptography>=46.0.3
Requires-Dist: fake-useragent>=2.2.0
Requires-Dist: requests>=2.32.5
Requires-Dist: tqdm>=4.67.1
